jaxlpips/__init__.py
jaxlpips/lpips.py
jaxlpips/utils.py
jaxlpips/modules/__init__.py
jaxlpips/modules/alexnet.py
jaxlpips/modules/vgg.py
jaxlpips-1.2.0.dist-info/licenses/LICENSE
jaxlpips-1.2.0.dist-info/METADATA
jaxlpips-1.2.0.dist-info/WHEEL
jaxlpips-1.2.0.dist-info/top_level.txt
jaxlpips-1.2.0.dist-info/RECORD
