Metadata-Version: 2.4
Name: jaxlpips
Version: 1.2.0
Summary: LPIPS perceptual loss for JAX
License: MIT License
Classifier: Intended Audience :: Science/Research
Classifier: License :: OSI Approved :: MIT License
Classifier: Programming Language :: Python :: 3
Requires-Python: >=3.11
License-File: LICENSE
Requires-Dist: flax>=0.12.0
Requires-Dist: huggingface-hub>=0.31.1
Requires-Dist: jax>=0.6.0
Requires-Dist: safetensors>=0.5.3
Provides-Extra: dev
Requires-Dist: lpips>=0.1.4; extra == "dev"
Requires-Dist: pytest>=8.3.5; extra == "dev"
Dynamic: license-file
